AUTHORS
LICENSE
MANIFEST.in
README
README.md
setup.py
autoscalebot/.DS_Store
autoscalebot/__init__.py
autoscalebot/__init__.pyc
autoscalebot/autoscale_settings.py.dist
autoscalebot/cli.py
autoscalebot/conf.py
autoscalebot/conf.pyc
autoscalebot/logger.py
autoscalebot/logger.pyc
autoscalebot/models.py
autoscalebot/models.pyc
autoscalebot/tasks.py
autoscalebot/tasks.pyc
autoscalebot/tests.py
autoscalebot/urls.py
autoscalebot/urls.pyc
autoscalebot/views.py
autoscalebot/views.pyc
autoscalebot.egg-info/PKG-INFO
autoscalebot.egg-info/SOURCES.txt
autoscalebot.egg-info/dependency_links.txt
autoscalebot.egg-info/entry_points.txt
autoscalebot.egg-info/not-zip-safe
autoscalebot.egg-info/requires.txt
autoscalebot.egg-info/top_level.txt
autoscalebot/backends/.DS_Store
autoscalebot/backends/__init__.py
autoscalebot/backends/notification/__init__.py
autoscalebot/backends/notification/base.py
autoscalebot/backends/notification/console.py
autoscalebot/backends/notification/django_email.py
autoscalebot/backends/notification/logger.py
autoscalebot/backends/notification/test.py
autoscalebot/fixtures/initial_data.json
autoscalebot/management/.DS_Store
autoscalebot/management/__init__.py
autoscalebot/management/__init__.pyc
autoscalebot/management/commands/.DS_Store
autoscalebot/management/commands/__init__.py
autoscalebot/management/commands/__init__.pyc
autoscalebot/management/commands/run_autoscalebot.py