Metadata-Version: 1.0
Name: autoscalebot
Version: 2.1
Summary: Automatic scaling of web dynos on paas services
Home-page: https://github.com/wieden-kennedy/autoscalebot.git
Author: Steven Skoczen
Author-email: steven.skoczen@wk.com
License: UNKNOWN
Platform: UNKNOWN
Classifier: Programming Language :: Python
Classifier: License :: OSI Approved :: BSD License
Classifier: Operating System :: OS Independent
Classifier: Development Status :: 4 - Beta
Classifier: Environment :: Web Environment
Classifier: Intended Audience :: Developers
Classifier: Topic :: Internet :: WWW/HTTP
Classifier: Topic :: Software Development :: Libraries :: Python Modules
